arcane/notification/__init__.py
arcane/notification/notification_config.py
arcane/notification/notification_pubsub.py
arcane/notification/types.py
arcane_notification-1.3.1.dist-info/METADATA
arcane_notification-1.3.1.dist-info/WHEEL
arcane_notification-1.3.1.dist-info/RECORD
